imports/__init__.py
imports/vlc.py
junlib-0.1.2.dist-info/licenses/LICENSE
junlib-0.1.2.dist-info/METADATA
junlib-0.1.2.dist-info/WHEEL
junlib-0.1.2.dist-info/top_level.txt
junlib-0.1.2.dist-info/RECORD
