Metadata-Version: 2.4
Name: junLib
Version: 0.1.2
Summary: 파이썬 유틸리티 라이브러리
Author: jslee7518
Author-email: jslee7518 <jslee7518@gmail.com>
License: MIT License
Requires-Python: >=3.8
License-File: LICENSE
Requires-Dist: pandas
Requires-Dist: moviepy
Requires-Dist: PyQt5
Requires-Dist: watchdog
Dynamic: author
Dynamic: license-file
Dynamic: requires-python
